{"slots": ["jeu. 1 avr. 13:00", "ven. 9 avr. 13:40"], "urls": ["https://partners.doctolib.fr/hopital-public/pontoise/ght-novo-ghcpo-chrd-vaccination-covid-19?pid=practice-162508&enable_cookies_consent=1", "https://partners.doctolib.fr/centre-de-sante/cergy/centre-de-vaccination-cergy-pontoise?pid=practice-164301&enable_cookies_consent=1"], "noms": ["Centre de vaccination - Centre Hospitalier Ren\u00e9 Dubos", "Centre de vaccination Linandes-Cordeliers/site des Linandes"], "scan_time": "29/03/2021 \u00e0 23h00", "last_dep_updated": "95"}